{
  "project_info": {
    "project_number": "372462933207",
    "firebase_url": "https://miips-7b784.firebaseio.com",
    "project_id": "miips-7b784",
    "storage_bucket": "miips-7b784.appspot.com"
  },
  "client": [
    {
      "client_info": {
        "mobilesdk_app_id": "1:372462933207:android:7795a421fbdd2624cf8c92",
        "android_client_info": {
          "package_name": "miips.com"
        }
      },
      "oauth_client": [
        {
          "client_id": "372462933207-kenal8rj7sash2ddmfvthefju2vvpah9.apps.googleusercontent.com",
          "client_type": 1,
          "android_info": {
            "package_name": "miips.com",
            "certificate_hash": "3118b1f9342d7f7ce673fe9c7ec3c82ea3c70f76"
          }
        },
        {
          "client_id": "372462933207-8cj08vspulkrve1k11rshq7smm0h1ijb.apps.googleusercontent.com",
          "client_type": 3
        }
      ],
      "api_key": [
        {
          "current_key": "AIzaSyDAstDWT5ueYK_F8wI1amhG7Pv0LN055vY"
        }
      ],
      "services": {
        "appinvite_service": {
          "other_platform_oauth_client": [
            {
              "client_id": "372462933207-8cj08vspulkrve1k11rshq7smm0h1ijb.apps.googleusercontent.com",
              "client_type": 3
            }
          ]
        }
      }
    }
  ],
  "configuration_version": "1"
}